nonebot_plugin_sqlalchemy/__init__.py
nonebot_plugin_sqlalchemy-0.2.2.dist-info/LICENSE
nonebot_plugin_sqlalchemy-0.2.2.dist-info/METADATA
nonebot_plugin_sqlalchemy-0.2.2.dist-info/WHEEL
nonebot_plugin_sqlalchemy-0.2.2.dist-info/RECORD
