Metadata-Version: 2.1
Name: nonebot-plugin-sqlalchemy
Version: 0.2.2
Summary: 
Home-page: https://github.com/ssttkkl/nonebot-plugin-sqlalchemy
License: MIT
Author: ssttkkl
Author-email: huang.wen.long@hotmail.com
Requires-Python: >=3.9,<4.0
Classifier: License :: OSI Approved :: MIT License
Classifier: Programming Language :: Python :: 3
Classifier: Programming Language :: Python :: 3.9
Classifier: Programming Language :: Python :: 3.10
Classifier: Programming Language :: Python :: 3.11
Requires-Dist: nonebot2 (>=2.0.0,<3.0.0)
Requires-Dist: sqlalchemy[asyncio] (>=2.0.0,<3.0.0)
Project-URL: Repository, https://github.com/ssttkkl/nonebot-plugin-sqlalchemy
